Metadata-Version: 1.1
Name: pancake
Version: 1.1.1
Summary: A Data Structure for Pangenomes -- Identification of Singletons and Core Regions Dependent on Pairwise Sequence Similarities
Home-page: https://bitbucket.org/CorinnaErnst/pancake
Author: Corinna Ernst
Author-email: corinna.ernst@uni-due.de
License: MIT
Platform: UNKNOWN
Classifier: Development Status :: 4 - Beta
Classifier: Environment :: Console
Classifier: Intended Audience :: Science/Research
Classifier: License :: OSI Approved :: MIT License
Classifier: Natural Language :: English
Classifier: Programming Language :: Python :: 3
Classifier: Topic :: Scientific/Engineering :: Bio-Informatics
